srbusapi/__init__.py
srbusapi/config.py
srbusapi/crypto.py
srbusapi/exceptions.py
srbusapi/py.typed
srbusapi/caching/__init__.py
srbusapi/caching/base_cache.py
srbusapi/caching/caching_decorators.py
srbusapi/caching/redis_cache.py
srbusapi/client/__init__.py
srbusapi/client/base.py
srbusapi/client/beograd.py
srbusapi/client/nis.py
srbusapi/client/novi_sad.py
srbusapi-0.1.3.dist-info/METADATA
srbusapi-0.1.3.dist-info/WHEEL
srbusapi-0.1.3.dist-info/licenses/LICENSE
srbusapi-0.1.3.dist-info/RECORD
