Metadata-Version: 2.4
Name: srbusapi
Version: 0.1.3
Summary: Add your description here
Project-URL: Source, https://github.com/dusaan-m/python-serbia-bus-api
Author-email: dusaan-m <dusanmilivojevic01@gmail.com>
License-File: LICENSE
Requires-Python: >=3.10
Requires-Dist: httpx>=0.28.1
Requires-Dist: pycryptodome>=3.21.0
Provides-Extra: redis
Requires-Dist: redis>=5.2.1; extra == 'redis'
